springernature_api_client/__init__.py
springernature_api_client/api_client.py
springernature_api_client/config.py
springernature_api_client/exceptions.py
springernature_api_client/logging_config.py
springernature_api_client/meta.py
springernature_api_client/metadata.py
springernature_api_client/openaccess.py
springernature_api_client/tdm.py
springernature_api_client/utils.py
springernature_api_client/version.py
springernature_api_client-0.0.9.dist-info/METADATA
springernature_api_client-0.0.9.dist-info/WHEEL
springernature_api_client-0.0.9.dist-info/licenses/LICENSE
springernature_api_client-0.0.9.dist-info/RECORD
