Metadata-Version: 2.4
Name: springernature_api_client
Version: 0.0.9
Summary: Springer Nature API Client
License: MIT
License-File: LICENSE
Keywords: API,Springer Nature,client,requests
Author: Springer Nature
Author-email: supportapi@springernature.com
Requires-Python: >=3.9
Classifier: License :: OSI Approved :: MIT License
Classifier: Operating System :: OS Independent
Classifier: Programming Language :: Python :: 3
Classifier: Programming Language :: Python :: 3.9
Classifier: Programming Language :: Python :: 3.10
Classifier: Programming Language :: Python :: 3.11
Classifier: Programming Language :: Python :: 3.12
Classifier: Programming Language :: Python :: 3.13
Classifier: Programming Language :: Python :: 3.14
Requires-Dist: openpyxl (>=3.1.0,<4.0.0)
Requires-Dist: package-name (>=0.1,<0.2)
Requires-Dist: pandas (>=2.0.0,<3.0.0)
Requires-Dist: python-dotenv (>=1.0.0,<2.0.0)
Requires-Dist: requests (>=2.32.5,<3.0.0)
